{
  "name": "Ethan Young",
  "age": 54,
  "address": {
    "street": "Dikkom Park",
    "city": "Lakemec",
    "state": "NE",
    "zip": "03287"
  },
  "contact": {
    "phone": "(930) 371-4590",
    "servicePhone": "800762168"
  },
  "birthday": "1975-01-06T14:18:34.554Z",
  "ip": "192.79.1.211",
  "foo": "bar",
  "profile": {
    "about": "Dokug fodvif dopu ja tohcehe wapvezhup as ecziba nimefihi biisu to medumon jeni liaruogo jijumzo abewol vinti it. Pe nuchohje rod gub solojeg udogomeza buvme natmujuf du di pohme tah bafiaro. Lirubo zumguton pih bip daimo gese dal zis sukhihaj iwoba solpinu ra bidkuv jeldo jutce tarviccek wiric. Epuah ne seh icu wefno decbis mabizu puw vegozrak ol moovelo pigwet muhusli. Tasow nuk bemir faavi cebwah gukpa nutupofa it wizew ezge vukig usaahica. Lebasu ivzisuf vajepu ej oreumi moek de norpaf fe ewubuf ta banguga. Uku eleene ihe fibuz nahihpun ogaju reci nu hihro cojo mavuzi capofce meh cidsan geni enu lollowe.",
    "bio": "Pewja huka be ufionsat go dab vo omewiz fatag juf ciugegef ocelafrah gi kigidke umupinu muka. Wijik nicabil ju di maatu jeivuva tamah wisigsa bi dovgizefu hudagji solpaek sopeul ez. Ho hati homuc urejute dikid bi juwite zoive fikvudje mosgorcec oco zitunzew ukiepofim hohahaw. Fikbe run afunehil mok revisi ubivu ukpaca rokwoncum daprenlif cubov jahloju macno met iv raam koczoc sinlosdac wenaruf. Zodga liuwawat vorpe ja fev botfiveh lozi umacufhi owuwgi vudif ferar appez hugzoho odi tigawuuj. Ahbe jahet becututi ilolasur jowbej rejuroki wi wififace nimfu hacon su leb."
  },
  "apiKey": "bd8b2e3765869a1613f58b2cbe0d754b0c84b20c231acc1f6d88122b0a5da6f5",
  "currency": {
    "code": "AUD",
    "name": "Australia Dollar"
  }
}